{
  "last_updated": "2026-02-01 12:00:00 UTC",
  "threshold_percent": 15,
  "total_screened": 90,
  "stocks_found": 5,
  "stocks": [
    {
      "ticker": "INTC",
      "name": "Intel Corporation",
      "sector": "Technology",
      "current_price": 22.45,
      "low_52week": 21.10,
      "high_52week": 51.28,
      "pct_above_low": 6.40,
      "range_position": 4.48,
      "pe_ratio": null,
      "market_cap": 96800000000,
      "dividend_yield": 0.0223,
      "market_cap_fmt": "$96.80B",
      "pe_ratio_fmt": "N/A",
      "dividend_yield_fmt": "2.23%"
    },
    {
      "ticker": "NKE",
      "name": "NIKE, Inc.",
      "sector": "Consumer Cyclical",
      "current_price": 71.50,
      "low_52week": 68.50,
      "high_52week": 107.43,
      "pct_above_low": 4.38,
      "range_position": 7.71,
      "pe_ratio": 22.5,
      "market_cap": 106500000000,
      "dividend_yield": 0.0195,
      "market_cap_fmt": "$106.50B",
      "pe_ratio_fmt": "22.50",
      "dividend_yield_fmt": "1.95%"
    },
    {
      "ticker": "PFE",
      "name": "Pfizer Inc.",
      "sector": "Healthcare",
      "current_price": 26.80,
      "low_52week": 24.85,
      "high_52week": 31.54,
      "pct_above_low": 7.85,
      "range_position": 29.16,
      "pe_ratio": 17.8,
      "market_cap": 151200000000,
      "dividend_yield": 0.0612,
      "market_cap_fmt": "$151.20B",
      "pe_ratio_fmt": "17.80",
      "dividend_yield_fmt": "6.12%"
    },
    {
      "ticker": "MMM",
      "name": "3M Company",
      "sector": "Industrials",
      "current_price": 105.20,
      "low_52week": 95.18,
      "high_52week": 137.65,
      "pct_above_low": 10.53,
      "range_position": 23.60,
      "pe_ratio": 12.4,
      "market_cap": 58200000000,
      "dividend_yield": 0.0285,
      "market_cap_fmt": "$58.20B",
      "pe_ratio_fmt": "12.40",
      "dividend_yield_fmt": "2.85%"
    },
    {
      "ticker": "VZ",
      "name": "Verizon Communications Inc.",
      "sector": "Communication Services",
      "current_price": 41.25,
      "low_52week": 37.59,
      "high_52week": 45.27,
      "pct_above_low": 9.74,
      "range_position": 47.66,
      "pe_ratio": 9.2,
      "market_cap": 173500000000,
      "dividend_yield": 0.0645,
      "market_cap_fmt": "$173.50B",
      "pe_ratio_fmt": "9.20",
      "dividend_yield_fmt": "6.45%"
    }
  ]
}
